fiction_outlines_api/__init__.py
fiction_outlines_api/apps.py
fiction_outlines_api/exceptions.py
fiction_outlines_api/mixins.py
fiction_outlines_api/models.py
fiction_outlines_api/rules.py
fiction_outlines_api/serializers.py
fiction_outlines_api/urls.py
fiction_outlines_api/views.py
fiction_outlines_api/static/css/fiction_outlines_api.css
fiction_outlines_api/static/js/fiction_outlines_api.js
fiction_outlines_api/templates/fiction_outlines_api/base.html
django_fiction_outlines_api-0.3.0.dist-info/AUTHORS.rst
django_fiction_outlines_api-0.3.0.dist-info/LICENSE
django_fiction_outlines_api-0.3.0.dist-info/METADATA
django_fiction_outlines_api-0.3.0.dist-info/WHEEL
django_fiction_outlines_api-0.3.0.dist-info/top_level.txt
django_fiction_outlines_api-0.3.0.dist-info/RECORD
