Metadata-Version: 2.1
Name: django-fiction-outlines-api
Version: 0.3.0
Summary: A RESTful JSON API for django-fiction-outlines. Part of the broader maceoutliner project.
Home-page: https://github.com/andrlik/django-fiction-outlines-api
Author: Daniel Andrlik
Author-email: daniel@andrlik.org
License: BSD
Project-URL: Documenation, http://django-fiction-outlines-api.readthedocs.io/en/latest/index.html
Project-URL: Source, https://github.com/maceoutliner/django-fiction-outlines-api/
Project-URL: Issue Tracker, https://github.com/maceoutliner/django-fiction-outlines-api/issues
Keywords: django-fiction-outlines-api
Platform: UNKNOWN
Classifier: Development Status :: 3 - Alpha
Classifier: Framework :: Django
Classifier: Intended Audience :: Developers
Classifier: License :: OSI Approved :: BSD License
Classifier: Natural Language :: English
Classifier: Programming Language :: Python :: 3.9
Classifier: Programming Language :: Python :: 3.10
Requires-Python: ~=3.9
License-File: LICENSE
License-File: AUTHORS.rst
Requires-Dist: django-fiction-outlines (>=0.4)
Requires-Dist: django-rest-framework-rules
Requires-Dist: djangorestframework
Requires-Dist: coreapi
Requires-Dist: django-filter
Requires-Dist: Markdown
